acfsa.py
mmat.py
setup.py
wrenlab/GO.py
wrenlab/R.py
wrenlab/__init__.py
wrenlab/correlation.pyx
wrenlab/distance.py
wrenlab/enrichment.py
wrenlab/experiment.py
wrenlab/function_prediction.py
wrenlab/impute.py
wrenlab/lm.py
wrenlab/ml.py
wrenlab/normalize.py
wrenlab/ontology.py
wrenlab/plot.py
wrenlab/signature.py
wrenlab/statistics.py
wrenlab.egg-info/PKG-INFO
wrenlab.egg-info/SOURCES.txt
wrenlab.egg-info/dependency_links.txt
wrenlab.egg-info/requires.txt
wrenlab.egg-info/top_level.txt
wrenlab/data/__init__.py
wrenlab/data/drugbank.py
wrenlab/data/gencode.py
wrenlab/data/signature.py
wrenlab/genome/BBI.pyx
wrenlab/genome/__init__.py
wrenlab/genome/gff3.py
wrenlab/genome/index.pyx
wrenlab/genome/types.pyx
wrenlab/ncbi/__init__.py
wrenlab/ncbi/gene.py
wrenlab/ncbi/medline.py
wrenlab/ncbi/taxonomy.py
wrenlab/ncbi/geo/__init__.py
wrenlab/ncbi/geo/db.py
wrenlab/ncbi/geo/label.py
wrenlab/ncbi/geo/metadb.py
wrenlab/sandbox/__init__.py
wrenlab/sandbox/jdw_correlations.py
wrenlab/sandbox/rnaseq_matrix.py
wrenlab/sandbox/rnaseq_processing.py
wrenlab/sandbox/tissue_gene_abundance.py
wrenlab/text/__init__.py
wrenlab/text/iridescent.py
wrenlab/text/nlp.py
wrenlab/text/ahocorasick/__init__.py
wrenlab/text/ahocorasick/algorithm.pyx
wrenlab/text/ahocorasick/types.pyx
wrenlab/util/__init__.py
wrenlab/util/aspera.py
wrenlab/util/kvstore.py
wrenlab/util/log.py
wrenlab/util/memoize.py
wrenlab/util/net.py
wrenlab/util/pandas.py
wrenlab/util/remote_table.py