Metadata-Version: 1.1
Name: wrenlab
Version: 0.1.2
Summary: Wren Lab bioinformatics utilities
Home-page: UNKNOWN
Author: Cory Giles
Author-email: mail@corygil.es
License: AGPLv3+
Platform: UNKNOWN
Classifier: Development Status :: 3 - Alpha
Classifier: Intended Audience :: Science/Research
Classifier: License :: OSI Approved :: GNU Affero General Public License v3 or later (AGPLv3+)
Classifier: Natural Language :: English
Classifier: Operating System :: POSIX
Classifier: Programming Language :: Python :: 3.5
Classifier: Topic :: Scientific/Engineering :: Bio-Informatics
